automatic_time_lapse_creator/__init__.py
automatic_time_lapse_creator/__init__pyi
automatic_time_lapse_creator/cache_manager.py
automatic_time_lapse_creator/cache_manager.pyi
automatic_time_lapse_creator/source.py
automatic_time_lapse_creator/source.pyi
automatic_time_lapse_creator/text_box.py
automatic_time_lapse_creator/text_box.pyi
automatic_time_lapse_creator/time_lapse_creator.py
automatic_time_lapse_creator/time_lapse_creator.pyi
automatic_time_lapse_creator/time_manager.py
automatic_time_lapse_creator/time_manager.pyi
automatic_time_lapse_creator/video_manager.py
automatic_time_lapse_creator/video_manager.pyi
automatic_time_lapse_creator/weather_station_info.py
automatic_time_lapse_creator/weather_station_info.pyi
automatic_time_lapse_creator/youtube_manager.py
automatic_time_lapse_creator/youtube_manager.pyi
automatic_time_lapse_creator/common/__init__.py
automatic_time_lapse_creator/common/__init__.pyi
automatic_time_lapse_creator/common/constants.py
automatic_time_lapse_creator/common/constants.pyi
automatic_time_lapse_creator/common/exceptions.py
automatic_time_lapse_creator/common/exceptions.pyi
automatic_time_lapse_creator/common/logger.py
automatic_time_lapse_creator/common/logger.pyi
automatic_time_lapse_creator/common/utils.py
automatic_time_lapse_creator/common/utils.pyi
automatic_time_lapse_creator-2.0.1.dist-info/LICENSE
automatic_time_lapse_creator-2.0.1.dist-info/METADATA
automatic_time_lapse_creator-2.0.1.dist-info/WHEEL
automatic_time_lapse_creator-2.0.1.dist-info/top_level.txt
automatic_time_lapse_creator-2.0.1.dist-info/RECORD
