Metadata-Version: 2.2
Name: automatic_time_lapse_creator
Version: 2.0.1
Summary: automatic_time_lapse_creator is a Python program for scraping images from a web cam url and converting them into a timelapse
Author-email: Kaloyan Peychev <kokoeverest@gmail.com>
Maintainer-email: Kaloyan Peychev <kokoeverest@gmail.com>
Project-URL: Repository, https://github.com/kokoeverest/Automatic-time-lapse-creator
Project-URL: Issues, https://github.com/kokoeverest/Automatic-time-lapse-creator/issues
Keywords: requests,astral,opencv,opencv-python,timelapse,video,mp4,webcam,youtube,upload,automation
Classifier: Intended Audience :: Developers
Classifier: Programming Language :: Python :: 3
Classifier: Programming Language :: Python :: 3.10
Classifier: Programming Language :: Python :: 3.11
Classifier: Programming Language :: Python :: 3.12
Classifier: Programming Language :: Python :: 3.13
Classifier: License :: OSI Approved :: MIT License
Classifier: Operating System :: OS Independent
Requires-Python: >=3.10
License-File: LICENSE
Requires-Dist: astral>=3.2
Requires-Dist: certifi>=2024.8.30
Requires-Dist: charset-normalizer>=3.4.0
Requires-Dist: colorama>=0.4.6
Requires-Dist: idna>=3.10
Requires-Dist: iniconfig>=2.0.0
Requires-Dist: numpy>=2.1.3
Requires-Dist: opencv-python>=4.10.0.84
Requires-Dist: packaging>=24.2
Requires-Dist: pluggy>=1.5.0
Requires-Dist: pytest>=8.3.3
Requires-Dist: requests>=2.32.3
Requires-Dist: tzdata>=2024.2
Requires-Dist: urllib3>=2.2.3
Requires-Dist: yt-dlp>=2025.1.26
Requires-Dist: google-api-core>=2.24.0
Requires-Dist: google-api-python-client>=2.156.0
Requires-Dist: google-auth>=2.37.0
Requires-Dist: google-auth-httplib2>=0.2.0
Requires-Dist: google-auth-oauthlib>=1.2.1
Requires-Dist: googleapis-common-protos>=1.66.0
